cpsim/__init__.py
cpsim/attack.py
cpsim/simulator.py
cpsim/controllers/LP_cvxpy.py
cpsim/controllers/LQR.py
cpsim/controllers/LQRSSE.py
cpsim/controllers/MPC_OSQP.py
cpsim/controllers/MPC_cvxpy.py
cpsim/controllers/PID.py
cpsim/controllers/PID_incremental.py
cpsim/controllers/__init__.py
cpsim/controllers/controller_base.py
cpsim/formal/__init__.py
cpsim/formal/gaussian_distribution.py
cpsim/formal/half_space.py
cpsim/formal/hyperplane.py
cpsim/formal/reachability.py
cpsim/formal/strip.py
cpsim/formal/zonotope.py
cpsim/info/Timer.py
cpsim/info/__init__.py
cpsim/models/__init__.py
cpsim/models/linear/F16.py
cpsim/models/linear/__init__.py
cpsim/models/linear/aircraft_pitch.py
cpsim/models/linear/boeing747.py
cpsim/models/linear/heat.py
cpsim/models/linear/lane_keeping.py
cpsim/models/linear/motor_speed.py
cpsim/models/linear/platoon.py
cpsim/models/linear/quadrotor.py
cpsim/models/linear/quadruple_tank.py
cpsim/models/linear/rlc_circuit.py
cpsim/models/nonlinear/__init__.py
cpsim/models/nonlinear/compute_analytical_model.py
cpsim/models/nonlinear/compute_analytical_model_quad.py
cpsim/models/nonlinear/continuous_stirred_tank_reactor.py
cpsim/models/nonlinear/inverted_pendulum.py
cpsim/models/nonlinear/quad.py
cpsim/models/nonlinear/vessel.py
cpsim/observers/__init__.py
cpsim/observers/extended_kalman_filter.py
cpsim/observers/full_state_bound.py
cpsim/observers/full_state_bound_nonlinear.py
cpsim/observers/interval_helpers.py
cpsim/observers/kalman_filter.py
cpsim/utils/__init__.py
cpsim/utils/linearizer.py
cpsim-0.0.2.dist-info/LICENSE
cpsim-0.0.2.dist-info/METADATA
cpsim-0.0.2.dist-info/WHEEL
cpsim-0.0.2.dist-info/top_level.txt
cpsim-0.0.2.dist-info/RECORD
