Metadata-Version: 2.1
Name: cpsim
Version: 0.0.2
Summary: Simulation and Security Toolbox for Cyber-Physical Systems
Author-email: Lin Zhang <lzhan120@syr.edu>
Maintainer-email: Mengyu Liu <mliu71@syr.edu>
License: MIT License
Project-URL: homepage, https://sim.cpsec.org/en/latest/
Project-URL: documentation, https://sim.cpsec.org/en/latest/
Project-URL: repository, https://github.com/lion-zhang/CPSim/
Project-URL: Bug Tracker, https://github.com/lion-zhang/CPSim/issues
Keywords: cyber-physical system,control,simulation,security,CPS
Classifier: Programming Language :: Python :: 3
Classifier: License :: OSI Approved :: MIT License
Classifier: Operating System :: OS Independent
Requires-Python: >=3.7
License-File: LICENSE
Requires-Dist: scipy (>=1.9)
Requires-Dist: numpy
Requires-Dist: cvxpy
Requires-Dist: matplotlib
Provides-Extra: doc
Requires-Dist: sphinx ; extra == 'doc'
Requires-Dist: sphinx-rtd-theme ; extra == 'doc'
Provides-Extra: interval
Requires-Dist: pyinterval ; extra == 'interval'
